{
  "id": "18b422f0-4436-4ecd-aee0-59206595c81f",
  "prevId": "00000000-0000-0000-0000-000000000000",
  "version": "7",
  "dialect": "postgresql",
  "tables": {
    "public.provider_models": {
      "name": "provider_models",
      "schema": "",
      "columns": {
        "id": {
          "name": "id",
          "type": "integer",
          "primaryKey": true,
          "notNull": true,
          "identity": {
            "type": "always",
            "name": "provider_models_id_seq",
            "schema": "public",
            "increment": "1",
            "startWith": "1",
            "minValue": "1",
            "maxValue": "2147483647",
            "cache": "1",
            "cycle": false
          }
        },
        "name": {
          "name": "name",
          "type": "varchar(255)",
          "primaryKey": false,
          "notNull": true
        },
        "provider_id": {
          "name": "provider_id",
          "type": "varchar(255)",
          "primaryKey": false,
          "notNull": true
        },
        "model_id": {
          "name": "model_id",
          "type": "varchar(255)",
          "primaryKey": false,
          "notNull": true
        },
        "created_at": {
          "name": "created_at",
          "type": "timestamp",
          "primaryKey": false,
          "notNull": false,
          "default": "now()"
        },
        "updated_at": {
          "name": "updated_at",
          "type": "timestamp",
          "primaryKey": false,
          "notNull": false,
          "default": "now()"
        },
        "is_default": {
          "name": "is_default",
          "type": "boolean",
          "primaryKey": false,
          "notNull": true,
          "default": false
        },
        "is_enabled": {
          "name": "is_enabled",
          "type": "boolean",
          "primaryKey": false,
          "notNull": true,
          "default": true
        }
      },
      "indexes": {},
      "foreignKeys": {
        "provider_models_provider_id_providers_provider_id_fk": {
          "name": "provider_models_provider_id_providers_provider_id_fk",
          "tableFrom": "provider_models",
          "tableTo": "providers",
          "columnsFrom": [
            "provider_id"
          ],
          "columnsTo": [
            "provider_id"
          ],
          "onDelete": "cascade",
          "onUpdate": "no action"
        }
      },
      "compositePrimaryKeys": {},
      "uniqueConstraints": {
        "provider_models_model_id_unique": {
          "name": "provider_models_model_id_unique",
          "nullsNotDistinct": false,
          "columns": [
            "model_id"
          ]
        },
        "provider_id_model_id_unique": {
          "name": "provider_id_model_id_unique",
          "nullsNotDistinct": false,
          "columns": [
            "provider_id",
            "model_id"
          ]
        }
      },
      "policies": {},
      "checkConstraints": {},
      "isRLSEnabled": false
    },
    "public.providers": {
      "name": "providers",
      "schema": "",
      "columns": {
        "id": {
          "name": "id",
          "type": "integer",
          "primaryKey": true,
          "notNull": true,
          "identity": {
            "type": "always",
            "name": "providers_id_seq",
            "schema": "public",
            "increment": "1",
            "startWith": "1",
            "minValue": "1",
            "maxValue": "2147483647",
            "cache": "1",
            "cycle": false
          }
        },
        "name": {
          "name": "name",
          "type": "varchar(255)",
          "primaryKey": false,
          "notNull": true
        },
        "provider_id": {
          "name": "provider_id",
          "type": "varchar(255)",
          "primaryKey": false,
          "notNull": true
        },
        "base_url": {
          "name": "base_url",
          "type": "varchar(255)",
          "primaryKey": false,
          "notNull": false
        },
        "api_key": {
          "name": "api_key",
          "type": "text",
          "primaryKey": false,
          "notNull": true
        },
        "image_url": {
          "name": "image_url",
          "type": "varchar(255)",
          "primaryKey": false,
          "notNull": false
        },
        "created_at": {
          "name": "created_at",
          "type": "timestamp",
          "primaryKey": false,
          "notNull": false,
          "default": "now()"
        },
        "updated_at": {
          "name": "updated_at",
          "type": "timestamp",
          "primaryKey": false,
          "notNull": false,
          "default": "now()"
        },
        "iv": {
          "name": "iv",
          "type": "text",
          "primaryKey": false,
          "notNull": true
        }
      },
      "indexes": {},
      "foreignKeys": {},
      "compositePrimaryKeys": {},
      "uniqueConstraints": {
        "providers_name_unique": {
          "name": "providers_name_unique",
          "nullsNotDistinct": false,
          "columns": [
            "name"
          ]
        },
        "providers_provider_id_unique": {
          "name": "providers_provider_id_unique",
          "nullsNotDistinct": false,
          "columns": [
            "provider_id"
          ]
        }
      },
      "policies": {},
      "checkConstraints": {},
      "isRLSEnabled": false
    }
  },
  "enums": {},
  "schemas": {},
  "sequences": {},
  "roles": {},
  "policies": {},
  "views": {},
  "_meta": {
    "columns": {},
    "schemas": {},
    "tables": {}
  }
}